{"node":{"shortcode":"Cg5KzytJ6_h","id":2898395374792716257,"__typename":"GraphSidecar","is_video":false,"date":1659735675,"caption":"\ud83c\udf0aEl mar trasmite libertad \ud83d\ude0c, paz , \ud83d\ude0ctranquilidad \ud83d\ude42. \ud83d\udd76\n\ud83e\udef6\ud83d\udcabNos purifica el alma y esp\u00edritu, pero sobretodo nos regenera energ\u00edas !. \u2728\ud83c\udf1e \n\n#sunset \ud83c\udf1e #freedom #cute \ud83d\ude0c #selfie #selfies #pictureoftheday #colors\ud83c\udf08 #fitnessmotivation #fit #lgbt #lgbtq\ud83c\udf08 #fireislandpines","title":null,"viewer_has_liked":false,"edge_media_preview_like":{"count":3},"iphone_struct":{"taken_at":1659735675,"pk":2898395374792716257,"id":"2898395374792716257_7069995038","device_timestamp":1659735354684004,"media_type":8,"code":"Cg5KzytJ6_h","client_cache_key":"Mjg5ODM5NTM3NDc5MjcxNjI1Nw==.2","filter_type":0,"is_unified_video":false,"location":{"pk":261379077,"short_name":"Puerto L\u00f3pez","facebook_places_id":112143342131861,"external_source":"facebook_places","name":"Puerto L\u00f3pez","address":"","city":"","has_viewer_saved":false,"lng":-80.80937,"lat":-1.56012,"is_eligible_for_guides":true},"lat":-1.56012,"lng":-80.80937,"should_request_ads":false,"caption_is_edited":true,"like_and_view_counts_disabled":false,"commerciality_status":"not_commercial","is_paid_partnership":false,"is_visual_reply_commenter_notice_enabled":true,"original_media_has_visual_reply_media":false,"has_delayed_metadata":false,"comment_likes_enabled":false,"comment_threading_enabled":true,"has_more_comments":false,"max_num_visible_preview_comments":2,"preview_comments":[],"comments":[],"can_view_more_preview_comments":false,"comment_count":0,"hide_view_all_comment_entrypoint":false,"carousel_media_count":3,"carousel_media":[{"id":"2898395370699058977_7069995038","media_type":1,"image_versions2":{"candidates":[{"width":1440,"height":1630,"url":"https://scontent-lga3-1.cdninstagram.com/v/t51.2885-15/297416980_594340975676555_6419431550482914027_n.jpg?stp=dst-jpg_e35&_nc_ht=scontent-lga3-1.cdninstagram.com&_nc_cat=111&_nc_ohc=E8rI6F2YxKIAX8Tsbr4&edm=ABZsPhsBAAAA&ccb=7-5&ig_cache_key=Mjg5ODM5NTM3MDY5OTA1ODk3Nw%3D%3D.2-ccb7-5&oh=00_AT-F095etY3Z_7LoRof_nALlB_DRzGxYZHt9JW0N27j4DA&oe=62F4ECD6&_nc_sid=4efc9f"},{"width":1080,"height":1222,"url":"https://scontent-lga3-1.cdninstagram.com/v/t51.2885-15/297416980_594340975676555_6419431550482914027_n.jpg?stp=dst-jpg_e35_p1080x1080&_nc_ht=scontent-lga3-1.cdninstagram.com&_nc_cat=111&_nc_ohc=E8rI6F2YxKIAX8Tsbr4&edm=ABZsPhsBAAAA&ccb=7-5&ig_cache_key=Mjg5ODM5NTM3MDY5OTA1ODk3Nw%3D%3D.2-ccb7-5&oh=00_AT9veO0-kciqe5rmgEyqpg-isf8uWTDdEfcAMnaCZU4Hog&oe=62F4ECD6&_nc_sid=4efc9f"},{"width":750,"height":849,"url":"https://scontent-lga3-1.cdninstagram.com/v/t51.2885-15/297416980_594340975676555_6419431550482914027_n.jpg?stp=dst-jpg_e35_p750x750_sh0.08&_nc_ht=scontent-lga3-1.cdninstagram.com&_nc_cat=111&_nc_ohc=E8rI6F2YxKIAX8Tsbr4&edm=ABZsPhsBAAAA&ccb=7-5&ig_cache_key=Mjg5ODM5NTM3MDY5OTA1ODk3Nw%3D%3D.2-ccb7-5&oh=00_AT8gssh70SQM13XkR9N66Joxu_9GgFmlKBbN72MPjto8Qw&oe=62F4ECD6&_nc_sid=4efc9f"},{"width":640,"height":724,"url":"https://scontent-lga3-1.cdninstagram.com/v/t51.2885-15/297416980_594340975676555_6419431550482914027_n.jpg?stp=dst-jpg_e35_p640x640_sh0.08&_nc_ht=scontent-lga3-1.cdninstagram.com&_nc_cat=111&_nc_ohc=E8rI6F2YxKIAX8Tsbr4&edm=ABZsPhsBAAAA&ccb=7-5&ig_cache_key=Mjg5ODM5NTM3MDY5OTA1ODk3Nw%3D%3D.2-ccb7-5&oh=00_AT-D2244Rb6ErCAPWHnxu2JW_JUBZGbtGDOiVBMpvWYibg&oe=62F4ECD6&_nc_sid=4efc9f"},{"width":480,"height":543,"url":"https://scontent-lga3-1.cdninstagram.com/v/t51.2885-15/297416980_594340975676555_6419431550482914027_n.jpg?stp=dst-jpg_e35_p480x480&_nc_ht=scontent-lga3-1.cdninstagram.com&_nc_cat=111&_nc_ohc=E8rI6F2YxKIAX8Tsbr4&edm=ABZsPhsBAAAA&ccb=7-5&ig_cache_key=Mjg5ODM5NTM3MDY5OTA1ODk3Nw%3D%3D.2-ccb7-5&oh=00_AT8FNRRuav3Kl1wpQ4VCD_8wLY3kDl5b-s5IfInhYBW6kw&oe=62F4ECD6&_nc_sid=4efc9f"},{"width":320,"height":362,"url":"https://scontent-lga3-1.cdninstagram.com/v/t51.2885-15/297416980_594340975676555_6419431550482914027_n.jpg?stp=dst-jpg_e35_p320x320&_nc_ht=scontent-lga3-1.cdninstagram.com&_nc_cat=111&_nc_ohc=E8rI6F2YxKIAX8Tsbr4&edm=ABZsPhsBAAAA&ccb=7-5&ig_cache_key=Mjg5ODM5NTM3MDY5OTA1ODk3Nw%3D%3D.2-ccb7-5&oh=00_AT9ZOU3267HGXELmo5b-g3_OhvVNFAfHtCP2mCXvVxIH8g&oe=62F4ECD6&_nc_sid=4efc9f"},{"width":240,"height":272,"url":"https://scontent-lga3-1.cdninstagram.com/v/t51.2885-15/297416980_594340975676555_6419431550482914027_n.jpg?stp=dst-jpg_e35_p240x240&_nc_ht=scontent-lga3-1.cdninstagram.com&_nc_cat=111&_nc_ohc=E8rI6F2YxKIAX8Tsbr4&edm=ABZsPhsBAAAA&ccb=7-5&ig_cache_key=Mjg5ODM5NTM3MDY5OTA1ODk3Nw%3D%3D.2-ccb7-5&oh=00_AT8mq9u1My0ccIh54CB0e1xptWjdvO4lb7LCwBuC655nlQ&oe=62F4ECD6&_nc_sid=4efc9f"},{"width":1080,"height":1080,"url":"https://scontent-lga3-1.cdninstagram.com/v/t51.2885-15/297416980_594340975676555_6419431550482914027_n.jpg?stp=c0.95.1440.1440a_dst-jpg_e35_s1080x1080&_nc_ht=scontent-lga3-1.cdninstagram.com&_nc_cat=111&_nc_ohc=E8rI6F2YxKIAX8Tsbr4&edm=ABZsPhsBAAAA&ccb=7-5&ig_cache_key=Mjg5ODM5NTM3MDY5OTA1ODk3Nw%3D%3D.2-ccb7-5&oh=00_AT_j7q8OqUR8oju8_eNd_WEINROwVtU-9A_-yJssus3AcQ&oe=62F4ECD6&_nc_sid=4efc9f"},{"width":750,"height":750,"url":"https://scontent-lga3-1.cdninstagram.com/v/t51.2885-15/297416980_594340975676555_6419431550482914027_n.jpg?stp=c0.95.1440.1440a_dst-jpg_e35_s750x750_sh0.08&_nc_ht=scontent-lga3-1.cdninstagram.com&_nc_cat=111&_nc_ohc=E8rI6F2YxKIAX8Tsbr4&edm=ABZsPhsBAAAA&ccb=7-5&ig_cache_key=Mjg5ODM5NTM3MDY5OTA1ODk3Nw%3D%3D.2-ccb7-5&oh=00_AT8IMlN7imWz69t-n0w92jfuYcEN-WzmM0luKLyBqB4uKA&oe=62F4ECD6&_nc_sid=4efc9f"},{"width":640,"height":640,"url":"https://scontent-lga3-1.cdninstagram.com/v/t51.2885-15/297416980_594340975676555_6419431550482914027_n.jpg?stp=c0.95.1440.1440a_dst-jpg_e35_s640x640_sh0.08&_nc_ht=scontent-lga3-1.cdninstagram.com&_nc_cat=111&_nc_ohc=E8rI6F2YxKIAX8Tsbr4&edm=ABZsPhsBAAAA&ccb=7-5&ig_cache_key=Mjg5ODM5NTM3MDY5OTA1ODk3Nw%3D%3D.2-ccb7-5&oh=00_AT-1tRhMP_300qU_mXdS8zMAaLxVuV4CThXmRvlYRirbpg&oe=62F4ECD6&_nc_sid=4efc9f"},{"width":480,"height":480,"url":"https://scontent-lga3-1.cdninstagram.com/v/t51.2885-15/297416980_594340975676555_6419431550482914027_n.jpg?stp=c0.95.1440.1440a_dst-jpg_e35_s480x480&_nc_ht=scontent-lga3-1.cdninstagram.com&_nc_cat=111&_nc_ohc=E8rI6F2YxKIAX8Tsbr4&edm=ABZsPhsBAAAA&ccb=7-5&ig_cache_key=Mjg5ODM5NTM3MDY5OTA1ODk3Nw%3D%3D.2-ccb7-5&oh=00_AT8-oPQOnQxOK4jA8FWA931nF0aTkvPmvx81Z8rHpyhilQ&oe=62F4ECD6&_nc_sid=4efc9f"},{"width":320,"height":320,"url":"https://scontent-lga3-1.cdninstagram.com/v/t51.2885-15/297416980_594340975676555_6419431550482914027_n.jpg?stp=c0.95.1440.1440a_dst-jpg_e35_s320x320&_nc_ht=scontent-lga3-1.cdninstagram.com&_nc_cat=111&_nc_ohc=E8rI6F2YxKIAX8Tsbr4&edm=ABZsPhsBAAAA&ccb=7-5&ig_cache_key=Mjg5ODM5NTM3MDY5OTA1ODk3Nw%3D%3D.2-ccb7-5&oh=00_AT_1gGOwmjT8LWVuURR45obQ_fykNYJetH0ERm5TIwdt8g&oe=62F4ECD6&_nc_sid=4efc9f"},{"width":240,"height":240,"url":"https://scontent-lga3-1.cdninstagram.com/v/t51.2885-15/297416980_594340975676555_6419431550482914027_n.jpg?stp=c0.95.1440.1440a_dst-jpg_e35_s240x240&_nc_ht=scontent-lga3-1.cdninstagram.com&_nc_cat=111&_nc_ohc=E8rI6F2YxKIAX8Tsbr4&edm=ABZsPhsBAAAA&ccb=7-5&ig_cache_key=Mjg5ODM5NTM3MDY5OTA1ODk3Nw%3D%3D.2-ccb7-5&oh=00_AT-Rkg6fC37cIumR0rU-5q3w0Vf8Xq8yHnXAQbItK5VWQA&oe=62F4ECD6&_nc_sid=4efc9f"},{"width":150,"height":150,"url":"https://scontent-lga3-1.cdninstagram.com/v/t51.2885-15/297416980_594340975676555_6419431550482914027_n.jpg?stp=c0.95.1440.1440a_dst-jpg_e35_s150x150&_nc_ht=scontent-lga3-1.cdninstagram.com&_nc_cat=111&_nc_ohc=E8rI6F2YxKIAX8Tsbr4&edm=ABZsPhsBAAAA&ccb=7-5&ig_cache_key=Mjg5ODM5NTM3MDY5OTA1ODk3Nw%3D%3D.2-ccb7-5&oh=00_AT_oiR8pk-_xXT4INhkfLYCbz8A8uGYLsydSSidF0ltcjg&oe=62F4ECD6&_nc_sid=4efc9f"}]},"original_width":1440,"original_height":1630,"pk":2898395370699058977,"carousel_parent_id":"2898395374792716257_7069995038","commerciality_status":"not_commercial"},{"id":"2898395370698997288_7069995038","media_type":1,"image_versions2":{"candidates":[{"width":1440,"height":1630,"url":"https://scontent-lga3-1.cdninstagram.com/v/t51.2885-15/297589099_1097801597783157_2494951100531496726_n.jpg?stp=dst-jpg_e35&_nc_ht=scontent-lga3-1.cdninstagram.com&_nc_cat=109&_nc_ohc=MnUMqKxG6ncAX-nbdT9&edm=ABZsPhsBAAAA&ccb=7-5&ig_cache_key=Mjg5ODM5NTM3MDY5ODk5NzI4OA%3D%3D.2-ccb7-5&oh=00_AT9W6kqyBz3nUq8s7sVu196g5GUbSIuqXi4lOmCvp6E-hw&oe=62F4C43E&_nc_sid=4efc9f"},{"width":1080,"height":1222,"url":"https://scontent-lga3-1.cdninstagram.com/v/t51.2885-15/297589099_1097801597783157_2494951100531496726_n.jpg?stp=dst-jpg_e35_p1080x1080&_nc_ht=scontent-lga3-1.cdninstagram.com&_nc_cat=109&_nc_ohc=MnUMqKxG6ncAX-nbdT9&edm=ABZsPhsBAAAA&ccb=7-5&ig_cache_key=Mjg5ODM5NTM3MDY5ODk5NzI4OA%3D%3D.2-ccb7-5&oh=00_AT-Q-jchLyZ30-l_tKQOOvxgKUHY4TTv8pIjg6AMFadU5A&oe=62F4C43E&_nc_sid=4efc9f"},{"width":750,"height":849,"url":"https://scontent-lga3-1.cdninstagram.com/v/t51.2885-15/297589099_1097801597783157_2494951100531496726_n.jpg?stp=dst-jpg_e35_p750x750_sh0.08&_nc_ht=scontent-lga3-1.cdninstagram.com&_nc_cat=109&_nc_ohc=MnUMqKxG6ncAX-nbdT9&edm=ABZsPhsBAAAA&ccb=7-5&ig_cache_key=Mjg5ODM5NTM3MDY5ODk5NzI4OA%3D%3D.2-ccb7-5&oh=00_AT95qCETiZ6XT8952Lyhw7JSyJ2xxpNv35AtYmIeMA8Ilw&oe=62F4C43E&_nc_sid=4efc9f"},{"width":640,"height":724,"url":"https://scontent-lga3-1.cdninstagram.com/v/t51.2885-15/297589099_1097801597783157_2494951100531496726_n.jpg?stp=dst-jpg_e35_p640x640_sh0.08&_nc_ht=scontent-lga3-1.cdninstagram.com&_nc_cat=109&_nc_ohc=MnUMqKxG6ncAX-nbdT9&edm=ABZsPhsBAAAA&ccb=7-5&ig_cache_key=Mjg5ODM5NTM3MDY5ODk5NzI4OA%3D%3D.2-ccb7-5&oh=00_AT9ba-bw7imDelScBAYcA_vYQflA1Mw3Dxjh-LbZIbJ65g&oe=62F4C43E&_nc_sid=4efc9f"},{"width":480,"height":543,"url":"https://scontent-lga3-1.cdninstagram.com/v/t51.2885-15/297589099_1097801597783157_2494951100531496726_n.jpg?stp=dst-jpg_e35_p480x480&_nc_ht=scontent-lga3-1.cdninstagram.com&_nc_cat=109&_nc_ohc=MnUMqKxG6ncAX-nbdT9&edm=ABZsPhsBAAAA&ccb=7-5&ig_cache_key=Mjg5ODM5NTM3MDY5ODk5NzI4OA%3D%3D.2-ccb7-5&oh=00_AT9gDpVw4AGrQXY_zBMDto5tF3sC_DsHmPAHuO8Q1Ifkaw&oe=62F4C43E&_nc_sid=4efc9f"},{"width":320,"height":362,"url":"https://scontent-lga3-1.cdninstagram.com/v/t51.2885-15/297589099_1097801597783157_2494951100531496726_n.jpg?stp=dst-jpg_e35_p320x320&_nc_ht=scontent-lga3-1.cdninstagram.com&_nc_cat=109&_nc_ohc=MnUMqKxG6ncAX-nbdT9&edm=ABZsPhsBAAAA&ccb=7-5&ig_cache_key=Mjg5ODM5NTM3MDY5ODk5NzI4OA%3D%3D.2-ccb7-5&oh=00_AT_XAT1GYEVN0EFgzbPqBL9DtgdtlMFRDhObHb1xeLGxAg&oe=62F4C43E&_nc_sid=4efc9f"},{"width":240,"height":272,"url":"https://scontent-lga3-1.cdninstagram.com/v/t51.2885-15/297589099_1097801597783157_2494951100531496726_n.jpg?stp=dst-jpg_e35_p240x240&_nc_ht=scontent-lga3-1.cdninstagram.com&_nc_cat=109&_nc_ohc=MnUMqKxG6ncAX-nbdT9&edm=ABZsPhsBAAAA&ccb=7-5&ig_cache_key=Mjg5ODM5NTM3MDY5ODk5NzI4OA%3D%3D.2-ccb7-5&oh=00_AT9_ffWCPWmc1Gkvq0iM6DNo8muhrwogpuT6XAbnSWgJrw&oe=62F4C43E&_nc_sid=4efc9f"},{"width":1080,"height":1080,"url":"https://scontent-lga3-1.cdninstagram.com/v/t51.2885-15/297589099_1097801597783157_2494951100531496726_n.jpg?stp=c0.95.1440.1440a_dst-jpg_e35_s1080x1080&_nc_ht=scontent-lga3-1.cdninstagram.com&_nc_cat=109&_nc_ohc=MnUMqKxG6ncAX-nbdT9&edm=ABZsPhsBAAAA&ccb=7-5&ig_cache_key=Mjg5ODM5NTM3MDY5ODk5NzI4OA%3D%3D.2-ccb7-5&oh=00_AT-2TvskreVCZzCA-etCZWoTNdgMdYqF8fQrbrC6um7mFg&oe=62F4C43E&_nc_sid=4efc9f"},{"width":750,"height":750,"url":"https://scontent-lga3-1.cdninstagram.com/v/t51.2885-15/297589099_1097801597783157_2494951100531496726_n.jpg?stp=c0.95.1440.1440a_dst-jpg_e35_s750x750_sh0.08&_nc_ht=scontent-lga3-1.cdninstagram.com&_nc_cat=109&_nc_ohc=MnUMqKxG6ncAX-nbdT9&edm=ABZsPhsBAAAA&ccb=7-5&ig_cache_key=Mjg5ODM5NTM3MDY5ODk5NzI4OA%3D%3D.2-ccb7-5&oh=00_AT-dh1whTDu-hIMF4DJUi_WNv8XrQk099hgpLw86DA3EBQ&oe=62F4C43E&_nc_sid=4efc9f"},{"width":640,"height":640,"url":"https://scontent-lga3-1.cdninstagram.com/v/t51.2885-15/297589099_1097801597783157_2494951100531496726_n.jpg?stp=c0.95.1440.1440a_dst-jpg_e35_s640x640_sh0.08&_nc_ht=scontent-lga3-1.cdninstagram.com&_nc_cat=109&_nc_ohc=MnUMqKxG6ncAX-nbdT9&edm=ABZsPhsBAAAA&ccb=7-5&ig_cache_key=Mjg5ODM5NTM3MDY5ODk5NzI4OA%3D%3D.2-ccb7-5&oh=00_AT8pi4e1z5UwKxRxCRn0ecvRQtYZ_lZZl6w5O6CbNmgwWw&oe=62F4C43E&_nc_sid=4efc9f"},{"width":480,"height":480,"url":"https://scontent-lga3-1.cdninstagram.com/v/t51.2885-15/297589099_1097801597783157_2494951100531496726_n.jpg?stp=c0.95.1440.1440a_dst-jpg_e35_s480x480&_nc_ht=scontent-lga3-1.cdninstagram.com&_nc_cat=109&_nc_ohc=MnUMqKxG6ncAX-nbdT9&edm=ABZsPhsBAAAA&ccb=7-5&ig_cache_key=Mjg5ODM5NTM3MDY5ODk5NzI4OA%3D%3D.2-ccb7-5&oh=00_AT-xL0ZhoxJF_DwNQEta0kMMN_Zc0L2xZY_67LQrIiGdLQ&oe=62F4C43E&_nc_sid=4efc9f"},{"width":320,"height":320,"url":"https://scontent-lga3-1.cdninstagram.com/v/t51.2885-15/297589099_1097801597783157_2494951100531496726_n.jpg?stp=c0.95.1440.1440a_dst-jpg_e35_s320x320&_nc_ht=scontent-lga3-1.cdninstagram.com&_nc_cat=109&_nc_ohc=MnUMqKxG6ncAX-nbdT9&edm=ABZsPhsBAAAA&ccb=7-5&ig_cache_key=Mjg5ODM5NTM3MDY5ODk5NzI4OA%3D%3D.2-ccb7-5&oh=00_AT_9oehokO6zf0x24jkLazVZ8Gtf-2iAVFZRwANxlIL_lg&oe=62F4C43E&_nc_sid=4efc9f"},{"width":240,"height":240,"url":"https://scontent-lga3-1.cdninstagram.com/v/t51.2885-15/297589099_1097801597783157_2494951100531496726_n.jpg?stp=c0.95.1440.1440a_dst-jpg_e35_s240x240&_nc_ht=scontent-lga3-1.cdninstagram.com&_nc_cat=109&_nc_ohc=MnUMqKxG6ncAX-nbdT9&edm=ABZsPhsBAAAA&ccb=7-5&ig_cache_key=Mjg5ODM5NTM3MDY5ODk5NzI4OA%3D%3D.2-ccb7-5&oh=00_AT9pLwCtv8VJ9G1I38s2Rosf-YQg9_i6X8-HsBHieg0z_g&oe=62F4C43E&_nc_sid=4efc9f"},{"width":150,"height":150,"url":"https://scontent-lga3-1.cdninstagram.com/v/t51.2885-15/297589099_1097801597783157_2494951100531496726_n.jpg?stp=c0.95.1440.1440a_dst-jpg_e35_s150x150&_nc_ht=scontent-lga3-1.cdninstagram.com&_nc_cat=109&_nc_ohc=MnUMqKxG6ncAX-nbdT9&edm=ABZsPhsBAAAA&ccb=7-5&ig_cache_key=Mjg5ODM5NTM3MDY5ODk5NzI4OA%3D%3D.2-ccb7-5&oh=00_AT9oTm0QPdYdqajJCFlumc_mUyi_fS8hYiYENg6mesoLcA&oe=62F4C43E&_nc_sid=4efc9f"}]},"original_width":1440,"original_height":1630,"pk":2898395370698997288,"carousel_parent_id":"2898395374792716257_7069995038","commerciality_status":"not_commercial"},{"id":"2898395370782849696_7069995038","media_type":1,"image_versions2":{"candidates":[{"width":1440,"height":1630,"url":"https://scontent-lga3-1.cdninstagram.com/v/t51.2885-15/297273964_3261340997480331_5500251221911522212_n.jpg?stp=dst-jpg_e35&_nc_ht=scontent-lga3-1.cdninstagram.com&_nc_cat=103&_nc_ohc=Im8aARRz5ocAX-PL1pZ&edm=ABZsPhsBAAAA&ccb=7-5&ig_cache_key=Mjg5ODM5NTM3MDc4Mjg0OTY5Ng%3D%3D.2-ccb7-5&oh=00_AT-VpxpjYbqmljXLeZV0phx6Veo95zfWYPnTEf9sw9nNqw&oe=62F3FAC1&_nc_sid=4efc9f"},{"width":1080,"height":1222,"url":"https://scontent-lga3-1.cdninstagram.com/v/t51.2885-15/297273964_3261340997480331_5500251221911522212_n.jpg?stp=dst-jpg_e35_p1080x1080&_nc_ht=scontent-lga3-1.cdninstagram.com&_nc_cat=103&_nc_ohc=Im8aARRz5ocAX-PL1pZ&edm=ABZsPhsBAAAA&ccb=7-5&ig_cache_key=Mjg5ODM5NTM3MDc4Mjg0OTY5Ng%3D%3D.2-ccb7-5&oh=00_AT_K98CRRi6xSawTJQ6ZbA5tvnfmxFH0QK2scSdVWsqdhA&oe=62F3FAC1&_nc_sid=4efc9f"},{"width":750,"height":849,"url":"https://scontent-lga3-1.cdninstagram.com/v/t51.2885-15/297273964_3261340997480331_5500251221911522212_n.jpg?stp=dst-jpg_e35_p750x750_sh0.08&_nc_ht=scontent-lga3-1.cdninstagram.com&_nc_cat=103&_nc_ohc=Im8aARRz5ocAX-PL1pZ&edm=ABZsPhsBAAAA&ccb=7-5&ig_cache_key=Mjg5ODM5NTM3MDc4Mjg0OTY5Ng%3D%3D.2-ccb7-5&oh=00_AT97UMSn4iTKBwoRZqQ2btrCzr90gfWeaJkCmyCBO71exg&oe=62F3FAC1&_nc_sid=4efc9f"},{"width":640,"height":724,"url":"https://scontent-lga3-1.cdninstagram.com/v/t51.2885-15/297273964_3261340997480331_5500251221911522212_n.jpg?stp=dst-jpg_e35_p640x640_sh0.08&_nc_ht=scontent-lga3-1.cdninstagram.com&_nc_cat=103&_nc_ohc=Im8aARRz5ocAX-PL1pZ&edm=ABZsPhsBAAAA&ccb=7-5&ig_cache_key=Mjg5ODM5NTM3MDc4Mjg0OTY5Ng%3D%3D.2-ccb7-5&oh=00_AT8oAmQmGJjT0pgIpGps47toO3lK1yYYKYMFt9xmlVtfWA&oe=62F3FAC1&_nc_sid=4efc9f"},{"width":480,"height":543,"url":"https://scontent-lga3-1.cdninstagram.com/v/t51.2885-15/297273964_3261340997480331_5500251221911522212_n.jpg?stp=dst-jpg_e35_p480x480&_nc_ht=scontent-lga3-1.cdninstagram.com&_nc_cat=103&_nc_ohc=Im8aARRz5ocAX-PL1pZ&edm=ABZsPhsBAAAA&ccb=7-5&ig_cache_key=Mjg5ODM5NTM3MDc4Mjg0OTY5Ng%3D%3D.2-ccb7-5&oh=00_AT-oWuBR3ypFv03isej5cVI35vCUrCOF2j9RN77ZyQs1zw&oe=62F3FAC1&_nc_sid=4efc9f"},{"width":320,"height":362,"url":"https://scontent-lga3-1.cdninstagram.com/v/t51.2885-15/297273964_3261340997480331_5500251221911522212_n.jpg?stp=dst-jpg_e35_p320x320&_nc_ht=scontent-lga3-1.cdninstagram.com&_nc_cat=103&_nc_ohc=Im8aARRz5ocAX-PL1pZ&edm=ABZsPhsBAAAA&ccb=7-5&ig_cache_key=Mjg5ODM5NTM3MDc4Mjg0OTY5Ng%3D%3D.2-ccb7-5&oh=00_AT_BfTUhERJ-Ekh3vuLaAWA_r_QpsfXdH25UKL9IYaYFyw&oe=62F3FAC1&_nc_sid=4efc9f"},{"width":240,"height":272,"url":"https://scontent-lga3-1.cdninstagram.com/v/t51.2885-15/297273964_3261340997480331_5500251221911522212_n.jpg?stp=dst-jpg_e35_p240x240&_nc_ht=scontent-lga3-1.cdninstagram.com&_nc_cat=103&_nc_ohc=Im8aARRz5ocAX-PL1pZ&edm=ABZsPhsBAAAA&ccb=7-5&ig_cache_key=Mjg5ODM5NTM3MDc4Mjg0OTY5Ng%3D%3D.2-ccb7-5&oh=00_AT8r0nnEAilV4_ooRx05lNiOrMqu49XN35EN4b-Nq-K9Zw&oe=62F3FAC1&_nc_sid=4efc9f"},{"width":1080,"height":1080,"url":"https://scontent-lga3-1.cdninstagram.com/v/t51.2885-15/297273964_3261340997480331_5500251221911522212_n.jpg?stp=c0.95.1440.1440a_dst-jpg_e35_s1080x1080&_nc_ht=scontent-lga3-1.cdninstagram.com&_nc_cat=103&_nc_ohc=Im8aARRz5ocAX-PL1pZ&edm=ABZsPhsBAAAA&ccb=7-5&ig_cache_key=Mjg5ODM5NTM3MDc4Mjg0OTY5Ng%3D%3D.2-ccb7-5&oh=00_AT_-QZtLmlhj1OVsJLCSbU151GFYbhWgJ77kaas4n8nP3A&oe=62F3FAC1&_nc_sid=4efc9f"},{"width":750,"height":750,"url":"https://scontent-lga3-1.cdninstagram.com/v/t51.2885-15/297273964_3261340997480331_5500251221911522212_n.jpg?stp=c0.95.1440.1440a_dst-jpg_e35_s750x750_sh0.08&_nc_ht=scontent-lga3-1.cdninstagram.com&_nc_cat=103&_nc_ohc=Im8aARRz5ocAX-PL1pZ&edm=ABZsPhsBAAAA&ccb=7-5&ig_cache_key=Mjg5ODM5NTM3MDc4Mjg0OTY5Ng%3D%3D.2-ccb7-5&oh=00_AT9enp2qwKGD8pr0wHAU2Rv1QW2-WNC_F5PQcbJcXddj1A&oe=62F3FAC1&_nc_sid=4efc9f"},{"width":640,"height":640,"url":"https://scontent-lga3-1.cdninstagram.com/v/t51.2885-15/297273964_3261340997480331_5500251221911522212_n.jpg?stp=c0.95.1440.1440a_dst-jpg_e35_s640x640_sh0.08&_nc_ht=scontent-lga3-1.cdninstagram.com&_nc_cat=103&_nc_ohc=Im8aARRz5ocAX-PL1pZ&edm=ABZsPhsBAAAA&ccb=7-5&ig_cache_key=Mjg5ODM5NTM3MDc4Mjg0OTY5Ng%3D%3D.2-ccb7-5&oh=00_AT98WU1zHVZICUM117JrGYho1EgBWuoEJ5443ZWlk7VEBA&oe=62F3FAC1&_nc_sid=4efc9f"},{"width":480,"height":480,"url":"https://scontent-lga3-1.cdninstagram.com/v/t51.2885-15/297273964_3261340997480331_5500251221911522212_n.jpg?stp=c0.95.1440.1440a_dst-jpg_e35_s480x480&_nc_ht=scontent-lga3-1.cdninstagram.com&_nc_cat=103&_nc_ohc=Im8aARRz5ocAX-PL1pZ&edm=ABZsPhsBAAAA&ccb=7-5&ig_cache_key=Mjg5ODM5NTM3MDc4Mjg0OTY5Ng%3D%3D.2-ccb7-5&oh=00_AT_Od3wXRCp7dSxjqy7mq2O2RuEv7iGPbYuagztIuFr-LA&oe=62F3FAC1&_nc_sid=4efc9f"},{"width":320,"height":320,"url":"https://scontent-lga3-1.cdninstagram.com/v/t51.2885-15/297273964_3261340997480331_5500251221911522212_n.jpg?stp=c0.95.1440.1440a_dst-jpg_e35_s320x320&_nc_ht=scontent-lga3-1.cdninstagram.com&_nc_cat=103&_nc_ohc=Im8aARRz5ocAX-PL1pZ&edm=ABZsPhsBAAAA&ccb=7-5&ig_cache_key=Mjg5ODM5NTM3MDc4Mjg0OTY5Ng%3D%3D.2-ccb7-5&oh=00_AT9-cQv6544bTRLqhrsiYo5IKKNqgG3rZ3V8M9K3GDqvWg&oe=62F3FAC1&_nc_sid=4efc9f"},{"width":240,"height":240,"url":"https://scontent-lga3-1.cdninstagram.com/v/t51.2885-15/297273964_3261340997480331_5500251221911522212_n.jpg?stp=c0.95.1440.1440a_dst-jpg_e35_s240x240&_nc_ht=scontent-lga3-1.cdninstagram.com&_nc_cat=103&_nc_ohc=Im8aARRz5ocAX-PL1pZ&edm=ABZsPhsBAAAA&ccb=7-5&ig_cache_key=Mjg5ODM5NTM3MDc4Mjg0OTY5Ng%3D%3D.2-ccb7-5&oh=00_AT_zoaeMBaWCHtAZrC1VNq7EH8VEhU6lFTxrz0SDI4J64g&oe=62F3FAC1&_nc_sid=4efc9f"},{"width":150,"height":150,"url":"https://scontent-lga3-1.cdninstagram.com/v/t51.2885-15/297273964_3261340997480331_5500251221911522212_n.jpg?stp=c0.95.1440.1440a_dst-jpg_e35_s150x150&_nc_ht=scontent-lga3-1.cdninstagram.com&_nc_cat=103&_nc_ohc=Im8aARRz5ocAX-PL1pZ&edm=ABZsPhsBAAAA&ccb=7-5&ig_cache_key=Mjg5ODM5NTM3MDc4Mjg0OTY5Ng%3D%3D.2-ccb7-5&oh=00_AT8W6hXYcDtUgRfu_9Dq1ucTnJwTCpD2dO8GQ2VtxYW8xQ&oe=62F3FAC1&_nc_sid=4efc9f"}]},"original_width":1440,"original_height":1630,"pk":2898395370782849696,"carousel_parent_id":"2898395374792716257_7069995038","commerciality_status":"not_commercial"}],"can_see_insights_as_brand":false,"user":{"pk":7069995038,"username":"yonahmorales","full_name":"Jimmy C Morales","is_private":false,"profile_pic_url":"https://scontent-lga3-1.cdninstagram.com/v/t51.2885-19/290378456_3313506275641010_4133662208763194845_n.jpg?stp=dst-jpg_s150x150&_nc_ht=scontent-lga3-1.cdninstagram.com&_nc_cat=102&_nc_ohc=Wry5SJ4wOYIAX_cfJq-&edm=ABZsPhsBAAAA&ccb=7-5&oh=00_AT9_GSvFcsupvWhZCX2BJYqaayr51A3tbBt5cDQyveOTlg&oe=62F4FE36&_nc_sid=4efc9f","profile_pic_id":"2870312030705227312_7069995038","friendship_status":{"following":false,"outgoing_request":false,"is_bestie":false,"is_restricted":false,"is_feed_favorite":false},"has_anonymous_profile_picture":false,"is_unpublished":false,"is_favorite":false,"has_highlight_reels":false,"transparency_product_enabled":false,"account_badges":[],"fan_club_info":{"fan_club_id":null,"fan_club_name":null}},"can_viewer_reshare":true,"like_count":3,"has_liked":false,"top_likers":[],"facepile_top_likers":[],"likers":[{"pk":2166627691,"username":"cordovillazuloaga","full_name":"Isaac Cordovilla Zuloaga","is_private":true,"profile_pic_url":"https://scontent-lga3-1.cdninstagram.com/v/t51.2885-19/291967587_129822549512752_8661374000605538318_n.jpg?stp=dst-jpg_s150x150&_nc_ht=scontent-lga3-1.cdninstagram.com&_nc_cat=104&_nc_ohc=vCHHkrBoBxwAX8aefQn&edm=ABZsPhsBAAAA&ccb=7-5&oh=00_AT84O7Zl_x5My5q6-E3lhSbsI18uRrj7pbb7i6v0gFerUA&oe=62F41210&_nc_sid=4efc9f","profile_pic_id":"2876789871633992173_2166627691","is_verified":false},{"pk":1993398821,"username":"soyjosehernan","full_name":"Hernandez Jose","is_private":false,"profile_pic_url":"https://scontent-lga3-1.cdninstagram.com/v/t51.2885-19/273616113_655518665692225_3053554006228678838_n.jpg?stp=dst-jpg_s150x150&_nc_ht=scontent-lga3-1.cdninstagram.com&_nc_cat=101&_nc_ohc=tIHue3oXwe4AX_SJsKB&tn=QYt_bVmhlspHbF1V&edm=ABZsPhsBAAAA&ccb=7-5&oh=00_AT-qQzT8hpFVm3edAuVMeZ5RweEGnLsv941KlcZKrKbSuA&oe=62F51147&_nc_sid=4efc9f","profile_pic_id":"2770173731827613159_1993398821","is_verified":false},{"pk":7069995038,"username":"yonahmorales","full_name":"Jimmy C Morales","is_private":false,"profile_pic_url":"https://scontent-lga3-1.cdninstagram.com/v/t51.2885-19/290378456_3313506275641010_4133662208763194845_n.jpg?stp=dst-jpg_s150x150&_nc_ht=scontent-lga3-1.cdninstagram.com&_nc_cat=102&_nc_ohc=Wry5SJ4wOYIAX_cfJq-&edm=ABZsPhsBAAAA&ccb=7-5&oh=00_AT9_GSvFcsupvWhZCX2BJYqaayr51A3tbBt5cDQyveOTlg&oe=62F4FE36&_nc_sid=4efc9f","profile_pic_id":"2870312030705227312_7069995038","is_verified":false}],"photo_of_you":false,"is_organic_product_tagging_eligible":false,"caption":{"pk":17966007160825141,"user_id":7069995038,"text":"\ud83c\udf0aEl mar trasmite libertad \ud83d\ude0c, paz , \ud83d\ude0ctranquilidad \ud83d\ude42. \ud83d\udd76\n\ud83e\udef6\ud83d\udcabNos purifica el alma y esp\u00edritu, pero sobretodo nos regenera energ\u00edas !. \u2728\ud83c\udf1e \n\n#sunset \ud83c\udf1e #freedom #cute \ud83d\ude0c #selfie #selfies #pictureoftheday #colors\ud83c\udf08 #fitnessmotivation #fit #lgbt #lgbtq\ud83c\udf08 #fireislandpines","type":1,"created_at":1659735847,"created_at_utc":1659735847,"content_type":"comment","status":"Active","bit_flags":0,"did_report_as_spam":false,"share_enabled":false,"user":{"pk":7069995038,"username":"yonahmorales","full_name":"Jimmy C Morales","is_private":false,"profile_pic_url":"https://scontent-lga3-1.cdninstagram.com/v/t51.2885-19/290378456_3313506275641010_4133662208763194845_n.jpg?stp=dst-jpg_s150x150&_nc_ht=scontent-lga3-1.cdninstagram.com&_nc_cat=102&_nc_ohc=Wry5SJ4wOYIAX_cfJq-&edm=ABZsPhsBAAAA&ccb=7-5&oh=00_AT9_GSvFcsupvWhZCX2BJYqaayr51A3tbBt5cDQyveOTlg&oe=62F4FE36&_nc_sid=4efc9f","profile_pic_id":"2870312030705227312_7069995038","is_verified":false},"is_covered":false,"media_id":2898395374792716257,"has_translation":true,"private_reply_status":0},"comment_inform_treatment":{"should_have_inform_treatment":false,"text":"","url":null,"action_type":null},"sharing_friction_info":{"should_have_sharing_friction":false,"bloks_app_url":null,"sharing_friction_payload":null},"can_viewer_save":true,"is_in_profile_grid":false,"profile_grid_control_enabled":false,"organic_tracking_token":"eyJ2ZXJzaW9uIjo1LCJwYXlsb2FkIjp7ImlzX2FuYWx5dGljc190cmFja2VkIjp0cnVlLCJ1dWlkIjoiNWE5ZjQxYzIwYmY2NGEyNWE0ZGMwYzJjYTRlZjExZWIyODk4Mzk1Mzc0NzkyNzE2MjU3Iiwic2VydmVyX3Rva2VuIjoiMTY1OTczNjA4MzcyNXwyODk4Mzk1Mzc0NzkyNzE2MjU3fDU0NTcxMDUzMjQ4fDk4ZmU5YTYxNTdkZmU4MGY4NWZlMWY1ODc0MjY1OTcyYzcwZDZjYjY4Yjc1MWI0ZjU0ZTBjZjY5MWY1NzdiMzUifSwic2lnbmF0dXJlIjoiIn0=","has_shared_to_fb":0,"product_type":"carousel_container","deleted_reason":0,"integrity_review_decision":"pending","commerce_integrity_review_decision":null,"music_metadata":{"music_canonical_id":"0","audio_type":null,"music_info":null,"original_sound_info":null}},"edge_sidecar_to_children":{"edges":[{"node":{"display_url":"https://scontent-lga3-1.cdninstagram.com/v/t51.2885-15/297416980_594340975676555_6419431550482914027_n.jpg?stp=dst-jpg_e35&_nc_ht=scontent-lga3-1.cdninstagram.com&_nc_cat=111&_nc_ohc=E8rI6F2YxKIAX8Tsbr4&edm=ABZsPhsBAAAA&ccb=7-5&ig_cache_key=Mjg5ODM5NTM3MDY5OTA1ODk3Nw%3D%3D.2-ccb7-5&oh=00_AT-F095etY3Z_7LoRof_nALlB_DRzGxYZHt9JW0N27j4DA&oe=62F4ECD6&_nc_sid=4efc9f","is_video":false}},{"node":{"display_url":"https://scontent-lga3-1.cdninstagram.com/v/t51.2885-15/297589099_1097801597783157_2494951100531496726_n.jpg?stp=dst-jpg_e35&_nc_ht=scontent-lga3-1.cdninstagram.com&_nc_cat=109&_nc_ohc=MnUMqKxG6ncAX-nbdT9&edm=ABZsPhsBAAAA&ccb=7-5&ig_cache_key=Mjg5ODM5NTM3MDY5ODk5NzI4OA%3D%3D.2-ccb7-5&oh=00_AT9W6kqyBz3nUq8s7sVu196g5GUbSIuqXi4lOmCvp6E-hw&oe=62F4C43E&_nc_sid=4efc9f","is_video":false}},{"node":{"display_url":"https://scontent-lga3-1.cdninstagram.com/v/t51.2885-15/297273964_3261340997480331_5500251221911522212_n.jpg?stp=dst-jpg_e35&_nc_ht=scontent-lga3-1.cdninstagram.com&_nc_cat=103&_nc_ohc=Im8aARRz5ocAX-PL1pZ&edm=ABZsPhsBAAAA&ccb=7-5&ig_cache_key=Mjg5ODM5NTM3MDc4Mjg0OTY5Ng%3D%3D.2-ccb7-5&oh=00_AT-VpxpjYbqmljXLeZV0phx6Veo95zfWYPnTEf9sw9nNqw&oe=62F3FAC1&_nc_sid=4efc9f","is_video":false}}]},"owner":{"id":7069995038,"username":"yonahmorales","is_private":false,"full_name":"Jimmy C Morales","profile_pic_url_hd":"https://scontent-lga3-1.cdninstagram.com/v/t51.2885-19/290378456_3313506275641010_4133662208763194845_n.jpg?stp=dst-jpg_s150x150&_nc_ht=scontent-lga3-1.cdninstagram.com&_nc_cat=102&_nc_ohc=Wry5SJ4wOYIAX_cfJq-&edm=ABZsPhsBAAAA&ccb=7-5&oh=00_AT9_GSvFcsupvWhZCX2BJYqaayr51A3tbBt5cDQyveOTlg&oe=62F4FE36&_nc_sid=4efc9f","iphone_struct":{"pk":7069995038,"username":"yonahmorales","full_name":"Jimmy C Morales","is_private":false,"profile_pic_url":"https://scontent-lga3-1.cdninstagram.com/v/t51.2885-19/290378456_3313506275641010_4133662208763194845_n.jpg?stp=dst-jpg_s150x150&_nc_ht=scontent-lga3-1.cdninstagram.com&_nc_cat=102&_nc_ohc=Wry5SJ4wOYIAX_cfJq-&edm=ABZsPhsBAAAA&ccb=7-5&oh=00_AT9_GSvFcsupvWhZCX2BJYqaayr51A3tbBt5cDQyveOTlg&oe=62F4FE36&_nc_sid=4efc9f","profile_pic_id":"2870312030705227312_7069995038","friendship_status":{"following":false,"outgoing_request":false,"is_bestie":false,"is_restricted":false,"is_feed_favorite":false},"has_anonymous_profile_picture":false,"is_unpublished":false,"is_favorite":false,"has_highlight_reels":false,"transparency_product_enabled":false,"account_badges":[],"fan_club_info":{"fan_club_id":null,"fan_club_name":null}}}},"instaloader":{"version":"4.9.2","node_type":"Post"}}